Security_Layer_Package/__init__.py
Security_Layer_Package/api.py
Security_Layer_Package/models.py
Security_Layer_Package/security.py
Security_Layer_Package-1.0.7.dist-info/LICENSE
Security_Layer_Package-1.0.7.dist-info/METADATA
Security_Layer_Package-1.0.7.dist-info/WHEEL
Security_Layer_Package-1.0.7.dist-info/top_level.txt
Security_Layer_Package-1.0.7.dist-info/RECORD
