Metadata-Version: 2.1
Name: Security_Layer_Package
Version: 1.0.7
Summary: this is a description of my package.
Author: Rawaa Ahmed
Author-email: rawaa.ahmed@ejada.com
License-File: LICENSE
Requires-Dist: requests
